ttmerge/__init__.py
ttmerge/merging_model.py
ttmerge-0.0.4.dist-info/LICENSE
ttmerge-0.0.4.dist-info/METADATA
ttmerge-0.0.4.dist-info/WHEEL
ttmerge-0.0.4.dist-info/RECORD
