Metadata-Version: 2.3
Name: ttmerge
Version: 0.0.4
Summary: Efficiently select and merge expert LoRAs at Test-Time
License: MIT
Author: Ryo Bertolissi
Author-email: rbertolissi@ethz.ch
Requires-Python: >=3.10
Classifier: Development Status :: 4 - Beta
Classifier: Intended Audience :: Science/Research
Classifier: License :: OSI Approved :: MIT License
Classifier: Programming Language :: Python :: 3
Classifier: Programming Language :: Python :: 3.10
Classifier: Programming Language :: Python :: 3.11
Classifier: Programming Language :: Python :: 3.12
Classifier: Programming Language :: Python :: 3.13
Requires-Dist: safetensors (>=0.4.5,<0.5.0)
Requires-Dist: torch (>=2.5.0,<3.0.0)
Requires-Dist: tqdm (>=4.0.0,<5.0.0)
Project-URL: documentation, https://rbertolissi.github.io/ttmerge
Project-URL: repository, https://github.com/rbertolissi/ttmerge
